LICENSE.txt
MANIFEST.in
README.txt
setup.py
dist/pyvttbl-0.4.2.0/pyvttbl-0.4.2.0/LICENSE.txt
dist/pyvttbl-0.4.2.0/pyvttbl-0.4.2.0/README.txt
dist/pyvttbl-0.4.2.0/pyvttbl-0.4.2.0/setup.py
dist/pyvttbl-0.4.2.0/pyvttbl-0.4.2.0/build/lib/pyvttbl/__init__.py
dist/pyvttbl-0.4.2.0/pyvttbl-0.4.2.0/build/lib/pyvttbl/base.py
dist/pyvttbl-0.4.2.0/pyvttbl-0.4.2.0/build/lib/pyvttbl/examples/__init__.py
dist/pyvttbl-0.4.2.0/pyvttbl-0.4.2.0/build/lib/pyvttbl/examples/betweenAVOVA_omega-squared.py
dist/pyvttbl-0.4.2.0/pyvttbl-0.4.2.0/build/lib/pyvttbl/misc/SimpleHTML.py
dist/pyvttbl-0.4.2.0/pyvttbl-0.4.2.0/build/lib/pyvttbl/misc/__init__.py
dist/pyvttbl-0.4.2.0/pyvttbl-0.4.2.0/build/lib/pyvttbl/misc/support.py
dist/pyvttbl-0.4.2.0/pyvttbl-0.4.2.0/build/lib/pyvttbl/misc/texttable.py
dist/pyvttbl-0.4.2.0/pyvttbl-0.4.2.0/build/lib/pyvttbl/plotting/__init__.py
dist/pyvttbl-0.4.2.0/pyvttbl-0.4.2.0/build/lib/pyvttbl/plotting/_box_plot.py
dist/pyvttbl-0.4.2.0/pyvttbl-0.4.2.0/build/lib/pyvttbl/plotting/_histogram_plot.py
dist/pyvttbl-0.4.2.0/pyvttbl-0.4.2.0/build/lib/pyvttbl/plotting/_interaction_plot.py
dist/pyvttbl-0.4.2.0/pyvttbl-0.4.2.0/build/lib/pyvttbl/plotting/_scatter_matrix.py
dist/pyvttbl-0.4.2.0/pyvttbl-0.4.2.0/build/lib/pyvttbl/plotting/_scatter_plot.py
dist/pyvttbl-0.4.2.0/pyvttbl-0.4.2.0/build/lib/pyvttbl/plotting/support.py
dist/pyvttbl-0.4.2.0/pyvttbl-0.4.2.0/build/lib/pyvttbl/stats/__init__.py
dist/pyvttbl-0.4.2.0/pyvttbl-0.4.2.0/build/lib/pyvttbl/stats/_anova.py
dist/pyvttbl-0.4.2.0/pyvttbl-0.4.2.0/build/lib/pyvttbl/stats/_anova1way.py
dist/pyvttbl-0.4.2.0/pyvttbl-0.4.2.0/build/lib/pyvttbl/stats/_chisquare1way.py
dist/pyvttbl-0.4.2.0/pyvttbl-0.4.2.0/build/lib/pyvttbl/stats/_chisquare2way.py
dist/pyvttbl-0.4.2.0/pyvttbl-0.4.2.0/build/lib/pyvttbl/stats/_correlation.py
dist/pyvttbl-0.4.2.0/pyvttbl-0.4.2.0/build/lib/pyvttbl/stats/_descriptives.py
dist/pyvttbl-0.4.2.0/pyvttbl-0.4.2.0/build/lib/pyvttbl/stats/_histogram.py
dist/pyvttbl-0.4.2.0/pyvttbl-0.4.2.0/pyvttbl.egg-info/SOURCES.txt
dist/pyvttbl-0.4.2.0/pyvttbl-0.4.2.0/pyvttbl.egg-info/dependency_links.txt
dist/pyvttbl-0.4.2.0/pyvttbl-0.4.2.0/pyvttbl.egg-info/requires.txt
dist/pyvttbl-0.4.2.0/pyvttbl-0.4.2.0/pyvttbl.egg-info/top_level.txt
pyvttbl.egg-info/PKG-INFO
pyvttbl.egg-info/SOURCES.txt
pyvttbl.egg-info/dependency_links.txt
pyvttbl.egg-info/not-zip-safe
pyvttbl.egg-info/requires.txt
pyvttbl.egg-info/top_level.txt
